octodns/__init__.py
octodns/context.py
octodns/deprecation.py
octodns/equality.py
octodns/idna.py
octodns/manager.py
octodns/yaml.py
octodns/zone.py
octodns/cmds/__init__.py
octodns/cmds/args.py
octodns/cmds/compare.py
octodns/cmds/dump.py
octodns/cmds/report.py
octodns/cmds/sync.py
octodns/cmds/validate.py
octodns/cmds/versions.py
octodns/processor/__init__.py
octodns/processor/acme.py
octodns/processor/arpa.py
octodns/processor/base.py
octodns/processor/clamp.py
octodns/processor/filter.py
octodns/processor/meta.py
octodns/processor/ownership.py
octodns/processor/restrict.py
octodns/processor/spf.py
octodns/processor/templating.py
octodns/processor/trailing_dots.py
octodns/provider/__init__.py
octodns/provider/base.py
octodns/provider/plan.py
octodns/provider/yaml.py
octodns/record/__init__.py
octodns/record/a.py
octodns/record/aaaa.py
octodns/record/alias.py
octodns/record/base.py
octodns/record/caa.py
octodns/record/change.py
octodns/record/chunked.py
octodns/record/cname.py
octodns/record/dname.py
octodns/record/ds.py
octodns/record/dynamic.py
octodns/record/exception.py
octodns/record/geo.py
octodns/record/geo_data.py
octodns/record/https.py
octodns/record/ip.py
octodns/record/loc.py
octodns/record/mx.py
octodns/record/naptr.py
octodns/record/ns.py
octodns/record/ptr.py
octodns/record/rr.py
octodns/record/spf.py
octodns/record/srv.py
octodns/record/sshfp.py
octodns/record/subnet.py
octodns/record/svcb.py
octodns/record/target.py
octodns/record/tlsa.py
octodns/record/txt.py
octodns/record/uri.py
octodns/record/urlfwd.py
octodns/secret/__init__.py
octodns/secret/base.py
octodns/secret/environ.py
octodns/secret/exception.py
octodns/source/__init__.py
octodns/source/base.py
octodns/source/envvar.py
octodns/source/tinydns.py
octodns-1.14.0.dist-info/licenses/LICENSE
octodns-1.14.0.dist-info/METADATA
octodns-1.14.0.dist-info/WHEEL
octodns-1.14.0.dist-info/entry_points.txt
octodns-1.14.0.dist-info/top_level.txt
octodns-1.14.0.dist-info/RECORD
