Metadata-Version: 2.4
Name: octodns
Version: 1.14.0
Summary: OctoDNS: DNS as code - Tools for managing DNS across multiple providers
Home-page: https://github.com/octodns/octodns
Author: Ross McFarland
Author-email: rwmcfa1@gmail.com
License: MIT
Requires-Python: >=3.9
License-File: LICENSE
Requires-Dist: PyYaml>=4.2b1
Requires-Dist: dnspython>=2.2.1
Requires-Dist: fqdn>=1.5.0
Requires-Dist: idna>=3.3
Requires-Dist: natsort>=5.5.0
Requires-Dist: python-dateutil>=2.8.1
Provides-Extra: dev
Requires-Dist: pytest>=6.2.5; extra == "dev"
Requires-Dist: pytest-cov>=3.0.0; extra == "dev"
Requires-Dist: pytest-network>=0.0.1; extra == "dev"
Requires-Dist: black<25.0.0,>=24.3.0; extra == "dev"
Requires-Dist: build>=0.7.0; extra == "dev"
Requires-Dist: changelet; extra == "dev"
Requires-Dist: isort>=5.11.5; extra == "dev"
Requires-Dist: pycountry>=19.8.18; extra == "dev"
Requires-Dist: pycountry-convert>=0.7.2; extra == "dev"
Requires-Dist: pyflakes>=2.2.0; extra == "dev"
Requires-Dist: readme_renderer[md]>=26.0; extra == "dev"
Requires-Dist: twine>=3.4.2; extra == "dev"
Provides-Extra: docs
Requires-Dist: myst-parser>=4.0.1; extra == "docs"
Requires-Dist: Sphinx>=8.2.3; extra == "docs"
Requires-Dist: sphinxcontrib-mermaid>=1.0.0; extra == "docs"
Requires-Dist: sphinx-copybutton>=0.5.2; extra == "docs"
Requires-Dist: sphinx_rtd_theme; extra == "docs"
Dynamic: author
Dynamic: author-email
Dynamic: description
Dynamic: description-content-type
Dynamic: home-page
Dynamic: license
Dynamic: license-file
Dynamic: provides-extra
Dynamic: requires-dist
Dynamic: requires-python
Dynamic: summary
